CONTRIBUTING.md
LICENSE
MANIFEST.in
README.rst
setup.py
docs/HISTORY.txt
docs/INSTALL.txt
docs/LICENSE.GPL
docs/LICENSE.txt
eea/__init__.py
eea.graylogger.egg-info/PKG-INFO
eea.graylogger.egg-info/SOURCES.txt
eea.graylogger.egg-info/dependency_links.txt
eea.graylogger.egg-info/entry_points.txt
eea.graylogger.egg-info/namespace_packages.txt
eea.graylogger.egg-info/not-zip-safe
eea.graylogger.egg-info/requires.txt
eea.graylogger.egg-info/top_level.txt
eea/graylogger/__init__.py
eea/graylogger/component.xml
eea/graylogger/configure.zcml
eea/graylogger/datatypes.py
eea/graylogger/version.txt
eea/graylogger/tests/__init__.py
eea/graylogger/tests/base.py
eea/graylogger/tests/test_doctest.py