Metadata-Version: 2.1
Name: eea.graylogger
Version: 2.4
Summary: GELF (Graylog Extended Log Format) for Zope
Home-page: https://github.com/collective/eea.graylogger
Author: European Environment Agency: IDM2 A-Team
Author-email: eea-edw-a-team-alerts@googlegroups.com
License: GPL version 2
Keywords: EEA Add-ons Plone Zope
Platform: UNKNOWN
Classifier: Framework :: Plone :: 4.0
Classifier: Framework :: Plone :: 4.1
Classifier: Framework :: Plone :: 4.2
Classifier: Framework :: Plone :: 4.3
Classifier: Framework :: Plone :: 5.1
Classifier: Framework :: Plone :: 5.2
Classifier: Framework :: Plone :: Addon
Classifier: Framework :: Zope :: 2
Classifier: Framework :: Zope :: 4
Classifier: Framework :: Zope
Classifier: Programming Language :: Python :: 2.7
Classifier: Programming Language :: Python :: 3.6
Classifier: Programming Language :: Python :: 3.7
Classifier: Programming Language :: Python
Classifier: Topic :: Software Development :: Libraries :: Python Modules
Classifier: License :: OSI Approved :: GNU General Public License (GPL)
Provides-Extra: test
License-File: LICENSE
